fastmap/__init__.py
fastmap/_distances.py
fastmap/_fastmap.py
fastmap/_fastmap_funcs.py
fastmap/distances/__init__.py
fastmap/distances/_cosine.py
fastmap/distances/_helpers.py
fastmap/distances/_jaccard.py
fastmap/distances/_l1.py
fastmap/distances/_l2.py
fastmap/distances/_lev.py
utils/__init__.py
utils/_tools.py
FastMapy-0.0.1.dist-info/LICENSE
FastMapy-0.0.1.dist-info/METADATA
FastMapy-0.0.1.dist-info/WHEEL
FastMapy-0.0.1.dist-info/top_level.txt
FastMapy-0.0.1.dist-info/RECORD
