Metadata-Version: 2.1
Name: FastMapy
Version: 0.0.1
Summary: Python Implementation of the FastMap MDS technique.
Home-page: https://github.com/shawn-davis/FastMapy
Author: Shawn Davis
Author-email: shawndavis.lomod@gmail.com
License: GPL-3.0 License
Platform: UNKNOWN
Requires-Dist: numpy
Requires-Dist: pebble
